[
  {
    "type": "tweet",
    "id": "2070497386493833698",
    "url": "https://x.com/paulg/status/2070497386493833698",
    "twitterUrl": "https://twitter.com/paulg/status/2070497386493833698",
    "text": "@xeno_form Most writing. And, interestingly, most art too.",
    "source": "",
    "retweetCount": 0,
    "replyCount": 0,
    "likeCount": 1,
    "quoteCount": 0,
    "viewCount": 324,
    "createdAt": "Fri Jun 26 13:20:19 +0000 2026",
    "lang": "en",
    "bookmarkCount": 0,
    "isReply": true,
    "inReplyToId": "2070493668340039682",
    "conversationId": "2070489234675245496",
    "inReplyToUserId": null,
    "inReplyToUsername": null,
    "isPinned": false,
    "author": {
      "type": "user",
      "userName": "paulg",
      "url": "https://x.com/paulg",
      "twitterUrl": "https://twitter.com/paulg",
      "id": "183749519",
      "name": "Paul Graham",
      "isVerified": false,
      "isBlueVerified": true,
      "profilePicture": "https://pbs.twimg.com/profile_images/1824002576/pg-railsconf_normal.jpg",
      "coverPicture": "https://pbs.twimg.com/profile_banners/183749519/1401332683",
      "description": "",
      "location": "",
      "followers": 3666072,
      "following": 795,
      "status": "",
      "canDm": false,
      "canMediaTag": false,
      "createdAt": "Fri Aug 27 20:13:59 +0000 2010",
      "entities": {
        "description": {
          "urls": []
        },
        "url": {}
      },
      "fastFollowersCount": 0,
      "favouritesCount": 154579,
      "hasCustomTimelines": true,
      "isTranslator": false,
      "mediaCount": 1901,
      "statusesCount": 53384,
      "withheldInCountries": [],
      "affiliatesHighlightedLabel": {},
      "possiblySensitive": false,
      "pinnedTweetIds": [],
      "profile_bio": {},
      "isAutomated": false,
      "automatedBy": null
    },
    "extendedEntities": {},
    "card": null,
    "place": {},
    "entities": {
      "user_mentions": [
        {
          "id_str": "2049769044950294528",
          "indices": [
            0,
            10
          ],
          "name": "xeno",
          "screen_name": "xeno_form"
        }
      ]
    },
    "reply_to_user_results": null,
    "quoted_tweet_results": null,
    "quoted_tweet": null,
    "retweeted_tweet": null,
    "isConversationControlled": false,
    "searchTermIndex": 0
  },
  {
    "type": "tweet",
    "id": "2070497063159181685",
    "url": "https://x.com/paulg/status/2070497063159181685",
    "twitterUrl": "https://twitter.com/paulg/status/2070497063159181685",
    "text": "@maintcraft That statement will be true iff it's a tautology.",
    "source": "",
    "retweetCount": 0,
    "replyCount": 1,
    "likeCount": 2,
    "quoteCount": 0,
    "viewCount": 187,
    "createdAt": "Fri Jun 26 13:19:02 +0000 2026",
    "lang": "en",
    "bookmarkCount": 0,
    "isReply": true,
    "inReplyToId": "2070490214896726176",
    "conversationId": "2070489234675245496",
    "inReplyToUserId": null,
    "inReplyToUsername": null,
    "isPinned": false,
    "author": {
      "type": "user",
      "userName": "paulg",
      "url": "https://x.com/paulg",
      "twitterUrl": "https://twitter.com/paulg",
      "id": "183749519",
      "name": "Paul Graham",
      "isVerified": false,
      "isBlueVerified": true,
      "profilePicture": "https://pbs.twimg.com/profile_images/1824002576/pg-railsconf_normal.jpg",
      "coverPicture": "https://pbs.twimg.com/profile_banners/183749519/1401332683",
      "description": "",
      "location": "",
      "followers": 3666072,
      "following": 795,
      "status": "",
      "canDm": false,
      "canMediaTag": false,
      "createdAt": "Fri Aug 27 20:13:59 +0000 2010",
      "entities": {
        "description": {
          "urls": []
        },
        "url": {}
      },
      "fastFollowersCount": 0,
      "favouritesCount": 154579,
      "hasCustomTimelines": true,
      "isTranslator": false,
      "mediaCount": 1901,
      "statusesCount": 53384,
      "withheldInCountries": [],
      "affiliatesHighlightedLabel": {},
      "possiblySensitive": false,
      "pinnedTweetIds": [],
      "profile_bio": {},
      "isAutomated": false,
      "automatedBy": null
    },
    "extendedEntities": {},
    "card": null,
    "place": {},
    "entities": {
      "user_mentions": [
        {
          "id_str": "1892717706",
          "indices": [
            0,
            11
          ],
          "name": "Alexander",
          "screen_name": "maintcraft"
        }
      ]
    },
    "reply_to_user_results": null,
    "quoted_tweet_results": null,
    "quoted_tweet": null,
    "retweeted_tweet": null,
    "isConversationControlled": false,
    "searchTermIndex": 0
  }
]